MANIFEST.in
README.md
dev_requirements.txt
requirements.txt
setup.py
test_requirements.txt
version.txt
cloudshell/__init__.py
cloudshell/sdn/__init__.py
cloudshell/sdn/resource_driver_interface.py
cloudshell/sdn/odl/__init__.py
cloudshell/sdn/odl/client.py
cloudshell/sdn/odl/converter.py
cloudshell/sdn/odl/flows/__init__.py
cloudshell/sdn/odl/flows/autoload_flow.py
cloudshell/sdn/odl/flows/create_connectivity_flow.py
cloudshell/sdn/odl/flows/remove_connectivity_flow.py
cloudshell/sdn/odl/flows/remove_openflow_flow.py
cloudshell/sdn/odl/runners/__init__.py
cloudshell/sdn/odl/runners/autoload_runner.py
cloudshell/sdn/odl/runners/connectivity_runner.py
cloudshell/sdn/odl/runners/remove_openflow_runner.py
cloudshell/sdn/runners/__init__.py
cloudshell/sdn/runners/autoload_runner.py
cloudshell/sdn/runners/connectivity_runner.py
cloudshell/sdn/runners/remove_openflow_runner.py
cloudshell_sdn_odl.egg-info/PKG-INFO
cloudshell_sdn_odl.egg-info/SOURCES.txt
cloudshell_sdn_odl.egg-info/dependency_links.txt
cloudshell_sdn_odl.egg-info/requires.txt
cloudshell_sdn_odl.egg-info/top_level.txt
tests/__init__.py
tests/sdn/__init__.py
tests/sdn/odl/__init__.py
tests/sdn/odl/test_client.py